Metadata-Version: 2.1
Name: odoo13-addon-mgmtsystem-action-efficacy
Version: 13.0.1.0.1
Summary: Add information on the application of the Action.
Home-page: https://github.com/OCA/management-system
Author: Associazione PNLUG - Gruppo Odoo, Odoo Community Association (OCA)
Author-email: support@odoo-community.org
License: AGPL-3
Platform: UNKNOWN
Classifier: Programming Language :: Python
Classifier: Framework :: Odoo
Classifier: Framework :: Odoo :: 13.0
Classifier: License :: OSI Approved :: GNU Affero General Public License v3
Classifier: Development Status :: 4 - Beta
Requires-Python: >=3.5
Requires-Dist: odoo13-addon-mgmtsystem-action
Requires-Dist: odoo (<13.1dev,>=13.0a)
